{
  "type": "recipe",
  "id": "tabs",
  "file": {
    "name": "tabs.ts",
    "content": "import { defineSlotRecipe } from \"@pandacss/dev\";\r\n\r\nexport const tabs = defineSlotRecipe({\r\n\tclassName: \"dreamy-tabs\",\r\n\tdescription: \"Dreamy UI Tabs component\",\r\n\tjsx: [\"Tabs\", \"TabList\", \"Tab\", \"TabPanels\", \"TabPanel\"],\r\n\tslots: [\"root\", \"tabList\", \"tab\", \"tabPanels\", \"tabPanel\", \"tabIndicator\"],\r\n\tbase: {\r\n\t\troot: {\r\n\t\t\tdisplay: \"flex\"\r\n\t\t},\r\n\t\ttabList: {\r\n\t\t\twidth: \"100%\",\r\n\t\t\tmaxWidth: \"100%\",\r\n\t\t\tdisplay: \"flex\",\r\n\t\t\theight: \"fit\",\r\n\t\t\tgap: 2,\r\n\t\t\talignItems: \"center\",\r\n\t\t\tflexWrap: \"nowrap\",\r\n\t\t\t_scrollbar: {\r\n\t\t\t\tdisplay: \"none\"\r\n\t\t\t},\r\n\t\t\toverflowX: \"clip\",\r\n\t\t\toverflowClipMargin: \"10px\",\r\n\t\t\toverflowY: \"visible\",\r\n\t\t\tposition: \"relative\"\r\n\t\t},\r\n\t\ttab: {\r\n\t\t\tzIndex: 0,\r\n\t\t\tminWidth: 20,\r\n\t\t\tpaddingInline: 4,\r\n\t\t\tpaddingTop: 1,\r\n\t\t\tpaddingBottom: 1,\r\n\t\t\tborderRadius: \"none\",\r\n\t\t\tWebkitTapHighlightColor: \"transparent\",\r\n\t\t\t\"&[data-unselected=true]\": {\r\n\t\t\t\topacity: 1\r\n\t\t\t}\r\n\t\t},\r\n\t\ttabPanels: {\r\n\t\t\tpadding: 4\r\n\t\t},\r\n\t\ttabPanel: {},\r\n\t\ttabIndicator: {\r\n\t\t\tposition: \"absolute\",\r\n\t\t\tleft: 0,\r\n\t\t\tright: 0\r\n\t\t}\r\n\t},\r\n\tvariants: {\r\n\t\tvariant: {\r\n\t\t\tfilled: {\r\n\t\t\t\ttabList: {\r\n\t\t\t\t\twidth: \"fit-content\",\r\n\t\t\t\t\tpadding: 1,\r\n\t\t\t\t\tborderRadius: \"l3\",\r\n\t\t\t\t\tbackgroundColor: \"{colors.alpha.100}\"\r\n\t\t\t\t},\r\n\t\t\t\ttab: {\r\n\t\t\t\t\tborderRadius: \"l2\",\r\n\t\t\t\t\t_hover: {\r\n\t\t\t\t\t\tbackgroundColor: \"alpha.50!\"\r\n\t\t\t\t\t}\r\n\t\t\t\t},\r\n\t\t\t\ttabIndicator: {\r\n\t\t\t\t\tbackgroundColor: \"alpha.100\",\r\n\t\t\t\t\ttop: 0,\r\n\t\t\t\t\tbottom: 0,\r\n\t\t\t\t\tzIndex: -1\r\n\t\t\t\t}\r\n\t\t\t},\r\n\t\t\tunderline: {\r\n\t\t\t\ttabList: {\r\n\t\t\t\t\twidth: \"100%\",\r\n\t\t\t\t\tborderBottomWidth: 1,\r\n\t\t\t\t\tborderStyle: \"solid\",\r\n\t\t\t\t\tborderColor: \"{colors.border}\"\r\n\t\t\t\t},\r\n\t\t\t\ttabIndicator: {\r\n\t\t\t\t\tbackgroundColor: \"{colors.primary}\",\r\n\t\t\t\t\theight: \"2px\",\r\n\t\t\t\t\tbottom: \"-1px\",\r\n\t\t\t\t\tzIndex: 1\r\n\t\t\t\t},\r\n\t\t\t\ttab: {\r\n\t\t\t\t\toverflow: \"visible\",\r\n\t\t\t\t\tcolor: \"{colors.fg.medium}\",\r\n\t\t\t\t\t_hover: {\r\n\t\t\t\t\t\tbackground: \"transparent !important\",\r\n\t\t\t\t\t\tcolor: \"{colors.fg.max}\"\r\n\t\t\t\t\t},\r\n\t\t\t\t\t_selected: {\r\n\t\t\t\t\t\tcolor: \"{colors.fg}\"\r\n\t\t\t\t\t}\r\n\t\t\t\t}\r\n\t\t\t},\r\n\t\t\t\"filled-simple\": {\r\n\t\t\t\ttab: {\r\n\t\t\t\t\tborderRadius: \"l2\"\r\n\t\t\t\t},\r\n\t\t\t\ttabList: {\r\n\t\t\t\t\twidth: \"fit-content\"\r\n\t\t\t\t},\r\n\t\t\t\ttabIndicator: {\r\n\t\t\t\t\tbackgroundColor: \"{colors.alpha.100}\",\r\n\t\t\t\t\ttop: 0,\r\n\t\t\t\t\tbottom: 0\r\n\t\t\t\t}\r\n\t\t\t}\r\n\t\t},\r\n\t\tfitted: {\r\n\t\t\ttrue: {\r\n\t\t\t\ttabList: {\r\n\t\t\t\t\twidth: \"100%\"\r\n\t\t\t\t},\r\n\t\t\t\ttab: {\r\n\t\t\t\t\tflex: 1\r\n\t\t\t\t}\r\n\t\t\t}\r\n\t\t},\r\n\t\torientation: {\r\n\t\t\tvertical: {\r\n\t\t\t\troot: {\r\n\t\t\t\t\twidth: \"fit-content\",\r\n\t\t\t\t\tflexDirection: \"row\"\r\n\t\t\t\t},\r\n\t\t\t\ttabList: {\r\n\t\t\t\t\tflexDirection: \"column\"\r\n\t\t\t\t}\r\n\t\t\t},\r\n\t\t\thorizontal: {\r\n\t\t\t\troot: {\r\n\t\t\t\t\twidth: \"100%\",\r\n\t\t\t\t\tflexDirection: \"column\"\r\n\t\t\t\t},\r\n\t\t\t\ttabList: {\r\n\t\t\t\t\tflexDirection: \"row\"\r\n\t\t\t\t}\r\n\t\t\t}\r\n\t\t}\r\n\t},\r\n\tdefaultVariants: {\r\n\t\tvariant: \"filled\",\r\n\t\torientation: \"horizontal\"\r\n\t},\r\n\tcompoundVariants: [\r\n\t\t{\r\n\t\t\torientation: \"vertical\",\r\n\t\t\tvariant: \"underline\",\r\n\t\t\tcss: {\r\n\t\t\t\ttabList: {\r\n\t\t\t\t\twidth: \"fit-content\",\r\n\t\t\t\t\toverflow: \"visible\",\r\n\t\t\t\t\tborderBottomWidth: 0,\r\n\t\t\t\t\tborderRightWidth: \"1px\"\r\n\t\t\t\t},\r\n\t\t\t\ttab: {\r\n\t\t\t\t\twidth: \"100%\",\r\n\t\t\t\t\tjustifyContent: \"flex-start\"\r\n\t\t\t\t},\r\n\t\t\t\ttabIndicator: {\r\n\t\t\t\t\tleft: \"auto\",\r\n\t\t\t\t\theight: \"100%\",\r\n\t\t\t\t\tright: \"-1px\",\r\n\t\t\t\t\ttop: 0,\r\n\t\t\t\t\twidth: \"2px\"\r\n\t\t\t\t}\r\n\t\t\t}\r\n\t\t}\r\n\t]\r\n});\r\n"
  }
}